flasher_tests/__init__.py
flasher-0.0.1.dist-info/RECORD
flasher-0.0.1.dist-info/top_level.txt
flasher-0.0.1.dist-info/zip-safe
flasher-0.0.1.dist-info/METADATA
flasher-0.0.1.dist-info/metadata.json
flasher-0.0.1.dist-info/DESCRIPTION.rst
flasher-0.0.1.dist-info/entry_points.txt
flasher-0.0.1.dist-info/WHEEL
flasher/subscriber.py
flasher/publisher.py
flasher/flash.py
flasher/__init__.py
