Metadata-Version: 2.0
Name: flasher
Version: 0.0.1
Summary: Build-Light controler designed to work with Blink(1) Light
Home-page: https://bitbucket.org/salimfadhley/flasher
Author: Salim Fadhley
Author-email: salimfadhley@gmail.com
License: MIT
Platform: UNKNOWN
Classifier: Development Status :: 2 - Pre-Alpha
Classifier: Environment :: Console
Classifier: Intended Audience :: Developers
Classifier: License :: OSI Approved :: MIT License
Classifier: Natural Language :: English
Classifier: Operating System :: OS Independent
Classifier: Programming Language :: Python :: 3
Classifier: Topic :: Software Development :: Testing
Requires-Dist: blink1
Requires-Dist: pyzmq
Requires-Dist: tornado
